fitchain/__init__.py
fitchain/connector.py
fitchain/constants.py
fitchain/crypto.py
fitchain/data_template.py
fitchain/datasource_faker.py
fitchain/dummy_data.py
fitchain/extract_geometry.py
fitchain/keras.py
fitchain/project.py
fitchain/schema_extractor.py
fitchain/sklearn.py
fitchain-0.0.20.dist-info/LICENSE.txt
fitchain-0.0.20.dist-info/METADATA
fitchain-0.0.20.dist-info/WHEEL
fitchain-0.0.20.dist-info/top_level.txt
fitchain-0.0.20.dist-info/RECORD
