Metadata-Version: 2.1
Name: fitchain
Version: 0.0.20
Summary: Fitchain Python Client
Home-page: https://bitbucket.org/fitchain/fitchain-sdk-python
Author: Fitchain
Author-email: hello@fitchain.io
License: Proprietary
Keywords: fitchain data client
Platform: UNKNOWN
Classifier: Development Status :: 3 - Alpha
Classifier: Topic :: Utilities
Requires-Dist: pandas
Requires-Dist: numpy
Requires-Dist: faker
Requires-Dist: requests
Requires-Dist: pyyaml
Requires-Dist: joblib
Requires-Dist: filemagic
Requires-Dist: pprint
Requires-Dist: keras
Requires-Dist: Pillow
